endi_oidc_provider/__init__.py
endi_oidc_provider/config.py
endi_oidc_provider/exceptions.py
endi_oidc_provider/generators.py
endi_oidc_provider/layout.py
endi_oidc_provider/models.py
endi_oidc_provider/routes.py
endi_oidc_provider/scope_consumer.py
endi_oidc_provider/security.py
endi_oidc_provider/subscribers.py
endi_oidc_provider/template_api.py
endi_oidc_provider/util.py
endi_oidc_provider/plugin/__init__.py
endi_oidc_provider/plugin/security.py
endi_oidc_provider/plugin/views/__init__.py
endi_oidc_provider/plugin/views/client.py
endi_oidc_provider/plugin/views/forms.py
endi_oidc_provider/scripts/__init__.py
endi_oidc_provider/scripts/manager.py
endi_oidc_provider/templates/form_layout.pt
endi_oidc_provider/templates/logout.mako
endi_oidc_provider/templates/plugin/client.mako
endi_oidc_provider/tests/__init__.py
endi_oidc_provider/tests/conftest.py
endi_oidc_provider/tests/test_scope_consumer.py
endi_oidc_provider/tests/test_util.py
endi_oidc_provider/tests/views/__init__.py
endi_oidc_provider/tests/views/test_authorize.py
endi_oidc_provider/tests/views/test_token.py
endi_oidc_provider/tests/views/test_userinfo.py
endi_oidc_provider/views/__init__.py
endi_oidc_provider/views/authorize.py
endi_oidc_provider/views/index.py
endi_oidc_provider/views/login.py
endi_oidc_provider/views/logout.py
endi_oidc_provider/views/token.py
endi_oidc_provider/views/userinfo.py
endi_oidc_provider-6.3.1.dist-info/METADATA
endi_oidc_provider-6.3.1.dist-info/WHEEL
endi_oidc_provider-6.3.1.dist-info/entry_points.txt
endi_oidc_provider-6.3.1.dist-info/top_level.txt
endi_oidc_provider-6.3.1.dist-info/RECORD
