Metadata-Version: 2.1
Name: endi-oidc-provider
Version: 6.3.1
Summary: endi_oidc_provider
Home-page: UNKNOWN
Author: 
Author-email: 
License: UNKNOWN
Keywords: web wsgi bfg pylons pyramid
Platform: UNKNOWN
Classifier: Programming Language :: Python
Classifier: Framework :: Pyramid
Classifier: Topic :: Internet :: WWW/HTTP
Classifier: Topic :: Internet :: WWW/HTTP :: WSGI :: Application
Requires-Dist: pyramid
Requires-Dist: pyramid-chameleon
Requires-Dist: pyramid-debugtoolbar
Requires-Dist: pyramid-tm
Requires-Dist: SQLAlchemy
Requires-Dist: transaction
Requires-Dist: zope.sqlalchemy
Requires-Dist: waitress
Provides-Extra: dev
Requires-Dist: libsass ; extra == 'dev'
Provides-Extra: testing
Requires-Dist: WebTest (>=1.3.1) ; extra == 'testing'
Requires-Dist: pytest ; extra == 'testing'
Requires-Dist: pytest-cov ; extra == 'testing'
